gTdev/__init__.py
gTdev/gtInv.py
gTdev/gtcurve.py
gTdev/gtdevCommon.py
gTdev/gtfile.py
gTdev/gtmos.py
gtdev-1.6.2.dist-info/LICENSE
gtdev-1.6.2.dist-info/METADATA
gtdev-1.6.2.dist-info/WHEEL
gtdev-1.6.2.dist-info/top_level.txt
gtdev-1.6.2.dist-info/RECORD
