Metadata-Version: 2.1
Name: gtdev
Version: 1.6.2
Summary: 高效碳基测试运算模块
Home-page: https://gitee.com/lxwk1spectre/gdevsample
Author: Spectre Lee
Author-email: lxwk1spectre@foxmail.com
Classifier: Programming Language :: Python :: 3
Classifier: License :: OSI Approved :: MIT License
Classifier: Operating System :: OS Independent
License-File: LICENSE
